ibis_substrait/__init__.py
ibis_substrait/compiler/__init__.py
ibis_substrait/compiler/core.py
ibis_substrait/compiler/mapping.py
ibis_substrait/compiler/translate.py
ibis_substrait/extensions/__init__.py
ibis_substrait/extensions/extension_types.yaml
ibis_substrait/extensions/functions_aggregate_approx.yaml
ibis_substrait/extensions/functions_aggregate_generic.yaml
ibis_substrait/extensions/functions_arithmetic.yaml
ibis_substrait/extensions/functions_arithmetic_decimal.yaml
ibis_substrait/extensions/functions_boolean.yaml
ibis_substrait/extensions/functions_comparison.yaml
ibis_substrait/extensions/functions_datetime.yaml
ibis_substrait/extensions/functions_logarithmic.yaml
ibis_substrait/extensions/functions_rounding.yaml
ibis_substrait/extensions/functions_set.yaml
ibis_substrait/extensions/functions_string.yaml
ibis_substrait/extensions/type_variations.yaml
ibis_substrait/extensions/unknown.yaml
ibis_substrait/tests/__init__.py
ibis_substrait/tests/compiler/__init__.py
ibis_substrait/tests/compiler/conftest.py
ibis_substrait/tests/compiler/snapshots/test_tpch/test_compile/tpc_h01/tpc_h01.json
ibis_substrait/tests/compiler/snapshots/test_tpch/test_compile/tpc_h02/tpc_h02.json
ibis_substrait/tests/compiler/snapshots/test_tpch/test_compile/tpc_h03/tpc_h03.json
ibis_substrait/tests/compiler/snapshots/test_tpch/test_compile/tpc_h04/tpc_h04.json
ibis_substrait/tests/compiler/snapshots/test_tpch/test_compile/tpc_h05/tpc_h05.json
ibis_substrait/tests/compiler/snapshots/test_tpch/test_compile/tpc_h06/tpc_h06.json
ibis_substrait/tests/compiler/snapshots/test_tpch/test_compile/tpc_h07/tpc_h07.json
ibis_substrait/tests/compiler/snapshots/test_tpch/test_compile/tpc_h08/tpc_h08.json
ibis_substrait/tests/compiler/snapshots/test_tpch/test_compile/tpc_h09/tpc_h09.json
ibis_substrait/tests/compiler/snapshots/test_tpch/test_compile/tpc_h10/tpc_h10.json
ibis_substrait/tests/compiler/snapshots/test_tpch/test_compile/tpc_h11/tpc_h11.json
ibis_substrait-4.0.1.dist-info/LICENSE
ibis_substrait-4.0.1.dist-info/METADATA
ibis_substrait-4.0.1.dist-info/WHEEL
ibis_substrait-4.0.1.dist-info/RECORD
