Metadata-Version: 2.1
Name: ibis-substrait
Version: 4.0.1
Summary: Subtrait compiler for ibis
Home-page: https://github.com/ibis-project/ibis-substrait
License: Apache-2.0
Author: Ibis Contributors
Maintainer: Ibis Contributors
Requires-Python: >=3.9,<4
Classifier: Development Status :: 2 - Pre-Alpha
Classifier: Intended Audience :: Science/Research
Classifier: License :: OSI Approved :: Apache Software License
Classifier: Operating System :: OS Independent
Classifier: Programming Language :: Python
Classifier: Programming Language :: Python :: 3
Classifier: Programming Language :: Python :: 3.9
Classifier: Programming Language :: Python :: 3.10
Classifier: Programming Language :: Python :: 3.11
Classifier: Programming Language :: Python :: 3.12
Classifier: Topic :: Scientific/Engineering
Requires-Dist: ibis-framework (>=9,<10)
Requires-Dist: packaging (>=21.3)
Requires-Dist: pyyaml (>=5)
Requires-Dist: substrait (>=0.2.1)
Project-URL: Repository, https://github.com/ibis-project/ibis-substrait
